{
	"archive" : {},
	"artifacts" : 
	[
		{
			"path" : "libmatching.a"
		}
	],
	"backtrace" : 1,
	"backtraceGraph" : 
	{
		"commands" : 
		[
			"add_library"
		],
		"files" : 
		[
			"CMakeLists.txt"
		],
		"nodes" : 
		[
			{
				"file" : 0
			},
			{
				"command" : 0,
				"file" : 0,
				"line" : 8,
				"parent" : 0
			}
		]
	},
	"id" : "matching::@6890427a1f51a3e7e1df",
	"name" : "matching",
	"nameOnDisk" : "libmatching.a",
	"paths" : 
	{
		"build" : ".",
		"source" : "."
	},
	"sourceGroups" : 
	[
		{
			"name" : "Header Files",
			"sourceIndexes" : 
			[
				0,
				1,
				2,
				3,
				4
			]
		}
	],
	"sources" : 
	[
		{
			"backtrace" : 1,
			"path" : "src/LogOrderReporter.h",
			"sourceGroupIndex" : 0
		},
		{
			"backtrace" : 1,
			"path" : "src/MatchReporter.h",
			"sourceGroupIndex" : 0
		},
		{
			"backtrace" : 1,
			"path" : "src/MatchingEngine.h",
			"sourceGroupIndex" : 0
		},
		{
			"backtrace" : 1,
			"path" : "src/OrderReport.h",
			"sourceGroupIndex" : 0
		},
		{
			"backtrace" : 1,
			"path" : "src/ThreadedLogReporter.h",
			"sourceGroupIndex" : 0
		}
	],
	"type" : "STATIC_LIBRARY"
}
